Metadata-Version: 1.1
Name: xologic
Version: 0.1.0
Summary: a tic tac toe logic to get winning team
Home-page: https://github.com/Abdulmumin1/xologic
Author: Abdulmumin Abdulkarim
Author-email: avdorr12345@gmail.com
License: BSD 2-clause
Platform: UNKNOWN
Classifier: Development Status :: 1 - Planning
Classifier: Intended Audience :: Developers
Classifier: License :: OSI Approved :: BSD License
Classifier: Operating System :: POSIX :: Linux
Classifier: Programming Language :: Python :: 3
Classifier: Programming Language :: Python :: 3.4
Classifier: Programming Language :: Python :: 3.5
